{"layoutId":"175832cf","title":"Origin Counts Pie","width":"100%","height":"100%","backgroundColor":"white","display":"flex","flexDirection":"row","layoutElements":[{"type":"pie","swimAttributes":{"width":"100%","innerRadius":"20%","outerRadius":"40%","hostUri":"ws://127.0.0.1:9001","nodeUri":"/aggregation","laneUri":"satellitesTypeCount","mapKey":"count","sliceColors":"rgba(10,89,124,0.7):rgba(74,199,254,0.7):rgba(21,151,206,0.7)","tickRadius":"40%","tickLength":"70px","baseAngle":"270deg","labelRadius":"50%","totalSlices":"3","tickColor":"transparent","labelColor":"transparent","color":"transparent"},"styleAttributes":{"flex-grow":"0"},"id":"5cd6a575","content":"","children":[],"hostUri":"warp://127.0.0.1:9001"}],"pageCss":"","pageJsFile":"","systemLayout":false,"lastEdit":1600470797150}